majormode/__init__.py
majormode/xebus/__init__.py
majormode/xebus/sis/__init__.py
majormode/xebus/sis/connector/__init__.py
majormode/xebus/sis/connector/constant/__init__.py
majormode/xebus/sis/connector/constant/vendor.py
majormode/xebus/sis/connector/sis_connector.py
xebus_sis_connector_core_library-1.3.5.dist-info/LICENSE.md
xebus_sis_connector_core_library-1.3.5.dist-info/WHEEL
xebus_sis_connector_core_library-1.3.5.dist-info/METADATA
xebus_sis_connector_core_library-1.3.5.dist-info/RECORD
